configextractor/__init__.py
configextractor/cli.py
configextractor/main.py
configextractor/frameworks/__init__.py
configextractor/frameworks/base.py
configextractor/frameworks/cape.py
configextractor/frameworks/maco.py
configextractor/frameworks/malduck.py.bak
configextractor/frameworks/mwcp.py
configextractor/frameworks/ratdecoder.py.bak
configextractor_py-1.1.14.dist-info/licenses/LICENSE.md
pipelines/publish.yaml
pipelines/test.yaml
tests/parsers/__init__.py
tests/parsers/cape_extractor.py
tests/parsers/maco_extractor.py
tests/parsers/mwcp_extractor.py
tests/venv_parsers/__init__.py
tests/venv_parsers/requirements.txt
configextractor_py-1.1.14.dist-info/METADATA
configextractor_py-1.1.14.dist-info/WHEEL
configextractor_py-1.1.14.dist-info/entry_points.txt
configextractor_py-1.1.14.dist-info/top_level.txt
configextractor_py-1.1.14.dist-info/RECORD
