Metadata-Version: 2.4
Name: configextractor-py
Version: 1.1.14
Summary: A library for extracting malware configurations across multiple frameworks
Author: cccs-rs
Maintainer: cccs-rs
License: MIT License
Project-URL: Repository, https://github.com/CybercentreCanada/configextractor-py
Project-URL: Issues, https://github.com/CybercentreCanada/configextractor-py/issues
Classifier: Development Status :: 5 - Production/Stable
Classifier: Intended Audience :: Developers
Classifier: Topic :: Software Development :: Libraries :: Python Modules
Classifier: License :: OSI Approved :: MIT License
Classifier: Programming Language :: Python :: 3.10
Classifier: Programming Language :: Python :: 3.11
Classifier: Programming Language :: Python :: 3.12
Requires-Python: >=3.8
License-File: LICENSE.md
Requires-Dist: cart
Requires-Dist: click
Requires-Dist: maco>=1.2.12
Requires-Dist: mwcfg
Requires-Dist: mwcp
Requires-Dist: setuptools
Dynamic: license-file
